frameio/__init__.py
frameio/account_permissions/__init__.py
frameio/account_permissions/client.py
frameio/account_permissions/raw_client.py
frameio/accounts/__init__.py
frameio/accounts/client.py
frameio/accounts/raw_client.py
frameio/client.py
frameio/comments/__init__.py
frameio/comments/client.py
frameio/comments/raw_client.py
frameio/comments/types/__init__.py
frameio/comments/types/comments_show_request_include.py
frameio/comments/types/create_comment_params_data.py
frameio/comments/types/update_comment_params_data.py
frameio/core/__init__.py
frameio/core/api_error.py
frameio/core/client_wrapper.py
frameio/core/custom_pagination.py
frameio/core/datetime_utils.py
frameio/core/file.py
frameio/core/force_multipart.py
frameio/core/http_client.py
frameio/core/http_response.py
frameio/core/http_sse/__init__.py
frameio/core/http_sse/_api.py
frameio/core/http_sse/_decoders.py
frameio/core/http_sse/_exceptions.py
frameio/core/http_sse/_models.py
frameio/core/jsonable_encoder.py
frameio/core/pagination.py
frameio/core/pydantic_utilities.py
frameio/core/query_encoder.py
frameio/core/remove_none_from_dict.py
frameio/core/request_options.py
frameio/core/serialization.py
frameio/core/unchecked_base_model.py
frameio/environment.py
frameio/errors/__init__.py
frameio/errors/bad_request_error.py
frameio/errors/forbidden_error.py
frameio/errors/not_found_error.py
frameio/errors/too_many_requests_error.py
frameio/errors/unauthorized_error.py
frameio/errors/unprocessable_entity_error.py
frameio/files/__init__.py
frameio/files/client.py
frameio/files/raw_client.py
frameio/files/types/__init__.py
frameio/files/types/file_copy_params_data.py
frameio/files/types/file_create_local_upload_params_data.py
frameio/files/types/file_create_params_data.py
frameio/files/types/file_create_remote_upload_params_data.py
frameio/files/types/file_move_params_data.py
frameio/files/types/file_update_params_data.py
frameio/files/types/files_copy_request_copy_comments.py
frameio/folders/__init__.py
frameio-0.0.28.dist-info/METADATA
frameio-0.0.28.dist-info/WHEEL
frameio-0.0.28.dist-info/RECORD
